<hierarchy rotation="0">
  <node index="0" text="" resource-id="" class="android.widget.FrameLayout" package="br.com.activity" content-desc="" checkable="false" checked="false" clickable="false" enabled="true" focusable="false" focused="false" scrollable="false" long-clickable="false" password="false" selected="false" visible-to-user="true" bounds="[28,565][1052,1292]">
    <node index="0" text="" resource-id="" class="android.widget.FrameLayout" package="br.com.activity" content-desc="" checkable="false" checked="false" clickable="false" enabled="true" focusable="false" focused="false" scrollable="false" long-clickable="false" password="false" selected="false" visible-to-user="true" bounds="[28,565][1052,1292]">
      <node index="0" text="" resource-id="android:id/content" class="android.widget.FrameLayout" package="br.com.activity" content-desc="" checkable="false" checked="false" clickable="false" enabled="true" focusable="false" focused="false" scrollable="false" long-clickable="false" password="false" selected="false" visible-to-user="true" bounds="[28,565][1052,1292]">
        <node index="0" text="" resource-id="android:id/parentPanel" class="android.widget.LinearLayout" package="br.com.activity" content-desc="" checkable="false" checked="false" clickable="false" enabled="true" focusable="false" focused="false" scrollable="false" long-clickable="false" password="false" selected="false" visible-to-user="true" bounds="[49,565][1031,1292]">
          <node index="0" text="" resource-id="android:id/customPanel" class="android.widget.FrameLayout" package="br.com.activity" content-desc="" checkable="false" checked="false" clickable="false" enabled="true" focusable="false" focused="false" scrollable="false" long-clickable="false" password="false" selected="false" visible-to-user="true" bounds="[49,565][1031,1143]">
            <node index="0" text="" resource-id="android:id/custom" class="android.widget.FrameLayout" package="br.com.activity" content-desc="" checkable="false" checked="false" clickable="false" enabled="true" focusable="false" focused="false" scrollable="false" long-clickable="false" password="false" selected="false" visible-to-user="true" bounds="[70,586][1010,1143]">
              <node index="0" text="" resource-id="android:id/timePicker" class="android.widget.TimePicker" package="br.com.activity" content-desc="" checkable="false" checked="false" clickable="false" enabled="true" focusable="false" focused="false" scrollable="false" long-clickable="false" password="false" selected="false" visible-to-user="true" bounds="[70,586][1010,1143]">
                <node index="0" text="" resource-id="android:id/timePickerLayout" class="android.widget.LinearLayout" package="br.com.activity" content-desc="" checkable="false" checked="false" clickable="false" enabled="true" focusable="false" focused="false" scrollable="false" long-clickable="false" password="false" selected="false" visible-to-user="true" bounds="[309,586][770,1143]">
                  <node index="0" text="" resource-id="" class="android.widget.LinearLayout" package="br.com.activity" content-desc="" checkable="false" checked="false" clickable="false" enabled="true" focusable="false" focused="false" scrollable="false" long-clickable="false" password="false" selected="false" visible-to-user="true" bounds="[330,586][749,1143]">
                    <node index="0" text="" resource-id="" class="android.widget.NumberPicker" package="br.com.activity" content-desc="" checkable="false" checked="false" clickable="false" enabled="true" focusable="false" focused="false" scrollable="true" long-clickable="false" password="false" selected="false" visible-to-user="true" bounds="[351,628][519,1101]">
                      <node index="0" text="09" resource-id="" class="android.widget.Button" package="br.com.activity" content-desc="" checkable="false" checked="false" clickable="true" enabled="true" focusable="false" focused="false" scrollable="false" long-clickable="true" password="false" selected="false" visible-to-user="true" bounds="[351,628][519,801]" />
                      <node index="1" text="10" resource-id="android:id/numberpicker_input" class="android.widget.EditText" package="br.com.activity" content-desc="" checkable="false" checked="false" clickable="true" enabled="true" focusable="true" focused="false" scrollable="false" long-clickable="true" password="false" selected="false" visible-to-user="true" bounds="[351,801][519,927]" />
                      <node index="2" text="11" resource-id="" class="android.widget.Button" package="br.com.activity" content-desc="" checkable="false" checked="false" clickable="true" enabled="true" focusable="false" focused="false" scrollable="false" long-clickable="true" password="false" selected="false" visible-to-user="true" bounds="[351,927][519,1101]" />
                    </node>
                    <node index="1" text=":" resource-id="android:id/divider" class="android.widget.TextView" package="br.com.activity" content-desc="" checkable="false" checked="false" clickable="false" enabled="true" focusable="false" focused="false" scrollable="false" long-clickable="false" password="false" selected="false" visible-to-user="true" bounds="[535,839][544,890]" />
                    <node index="2" text="" resource-id="" class="android.widget.NumberPicker" package="br.com.activity" content-desc="" checkable="false" checked="false" clickable="false" enabled="true" focusable="false" focused="false" scrollable="true" long-clickable="false" password="false" selected="false" visible-to-user="true" bounds="[560,628][728,1101]">
                      <node index="0" text="52" resource-id="" class="android.widget.Button" package="br.com.activity" content-desc="" checkable="false" checked="false" clickable="true" enabled="true" focusable="false" focused="false" scrollable="false" long-clickable="true" password="false" selected="false" visible-to-user="true" bounds="[560,628][728,801]" />
                      <node index="1" text="53" resource-id="android:id/numberpicker_input" class="android.widget.EditText" package="br.com.activity" content-desc="" checkable="false" checked="false" clickable="true" enabled="true" focusable="true" focused="false" scrollable="false" long-clickable="true" password="false" selected="false" visible-to-user="true" bounds="[560,801][728,927]" />
                      <node index="2" text="54" resource-id="" class="android.widget.Button" package="br.com.activity" content-desc="" checkable="false" checked="false" clickable="true" enabled="true" focusable="false" focused="false" scrollable="false" long-clickable="true" password="false" selected="false" visible-to-user="true" bounds="[560,927][728,1101]" />
                    </node>
                  </node>
                </node>
              </node>
            </node>
          </node>
          <node index="1" text="" resource-id="android:id/buttonPanel" class="android.widget.LinearLayout" package="br.com.activity" content-desc="" checkable="false" checked="false" clickable="false" enabled="true" focusable="false" focused="false" scrollable="false" long-clickable="false" password="false" selected="false" visible-to-user="true" bounds="[49,1143][1031,1292]">
            <node index="0" text="" resource-id="" class="android.widget.LinearLayout" package="br.com.activity" content-desc="" checkable="false" checked="false" clickable="false" enabled="true" focusable="false" focused="false" scrollable="false" long-clickable="false" password="false" selected="false" visible-to-user="true" bounds="[70,1145][1010,1271]">
              <node index="0" text="Cancel" resource-id="android:id/button2" class="android.widget.Button" package="br.com.activity" content-desc="" checkable="false" checked="false" clickable="true" enabled="true" focusable="true" focused="false" scrollable="false" long-clickable="false" password="false" selected="false" visible-to-user="true" bounds="[70,1145][539,1271]" />
              <node index="1" text="OK" resource-id="android:id/button1" class="android.widget.Button" package="br.com.activity" content-desc="" checkable="false" checked="false" clickable="true" enabled="true" focusable="true" focused="false" scrollable="false" long-clickable="false" password="false" selected="false" visible-to-user="true" bounds="[541,1145][1010,1271]" />
            </node>
          </node>
        </node>
      </node>
    </node>
  </node>
  </hierarchy>